{"createdAt":"2025-04-04T17:41:27.219Z","updatedAt":"2025-04-29T11:21:08.000Z","id":"oyOdzc0MXyPUk35K","name":"My workflow 2","active":false,"isArchived":false,"nodes":[{"parameters":{},"type":"n8n-nodes-base.manualTrigger","typeVersion":1,"position":[60,0],"id":"9ee5840b-d413-4991-842d-2f7fc0869d50","name":"When clicking ‘Test workflow’"},{"parameters":{},"type":"n8n-nodes-mcp.mcpClient","typeVersion":1,"position":[300,0],"id":"1b05aa6f-d5a4-49b9-83e4-037087945eff","name":"MCP Client","credentials":{"mcpClientApi":{"id":"iwycNoezt9ujFwqo","name":"MCP Milvus"}}}],"connections":{"When clicking ‘Test workflow’":{"main":[[{"node":"MCP Client","type":"main","index":0}]]}},"settings":{"executionOrder":"v1"},"staticData":null,"meta":{"templateCredsSetupCompleted":true},"pinData":{},"versionId":"705a8204-4741-44ad-930d-48c6656ae1cf","triggerCount":0,"tags":[]}